README.rst
setup.py
prtdep/__init__.py
prtdep/prtdep.py
prtdep.egg-info/PKG-INFO
prtdep.egg-info/SOURCES.txt
prtdep.egg-info/dependency_links.txt
prtdep.egg-info/entry_points.txt
prtdep.egg-info/requires.txt
prtdep.egg-info/top_level.txt