Metadata-Version: 1.1
Name: prtdep
Version: 0.0.2
Summary: CRUX ports dependencies helper.
Home-page: https://github.com/darko-poljak/prtdep
Author: Darko Poljak
Author-email: darko.poljak@gmail.com
License: GPLv3
Download-URL: https://github.com/darko-poljak/prtdep
Keywords: ports dependencies helper
Platform: OS Independent
Classifier: Development Status :: 4 - Beta
Classifier: License :: OSI Approved :: GNU General Public License v3 (GPLv3)
Classifier: Operating System :: OS Independent
Classifier: Topic :: System :: Systems Administration
